ezWrite/__init__.py
ezWrite/ezJson.py
ezWrite/ezWrite.py
ezWrite-0.0.6.dist-info/LICENSE
ezWrite-0.0.6.dist-info/METADATA
ezWrite-0.0.6.dist-info/WHEEL
ezWrite-0.0.6.dist-info/top_level.txt
ezWrite-0.0.6.dist-info/RECORD
