Metadata-Version: 2.1
Name: ezWrite
Version: 0.0.6
Summary: ezWrite to files package!
Author: Beere
Author-email: <beere.business@gmail.com>
Keywords: python,write,File,ezWrite,read,delete
Classifier: Development Status :: 3 - Alpha
Classifier: Intended Audience :: Developers
Classifier: Programming Language :: Python :: 3
Classifier: Operating System :: Unix
Classifier: Operating System :: MacOS :: MacOS X
Classifier: Operating System :: Microsoft :: Windows
License-File: LICENSE
Requires-Dist: cryptography
